Workbook

Sheet Raw Data
A1: Row ID | B1: Order ID | C1: Order Date | D1: Ship Date | E1: Ship Mode | F1: Customer ID | G1: Customer Name | H1: Segment | I1: Country | J1: City | K1: State | L1: Postal Code | M1: Region | N1: Product ID | O1: Category | P1: Sub-Category | Q1: Product Name | R1: Sales | S1: Quantity | T1: Discount | U1: Profit
A2: 1 | B2: CA-2016-152156 | C2: 42682 | D2: 42685 | E2: Second Class | F2: CG-12520 | G2: Claire Gute | H2: Consumer | I2: United States | J2: Henderson | K2: Kentucky | L2: 42420 | M2: South | N2: FUR-BO-10001798 | O2: Furniture | P2: Bookcases | Q2: Bush Somerset Collection Bookcase | R2: 261.96 | S2: 2 | T2: 0 | U2: 41.9136
A3: 2 | B3: CA-2016-152156 | C3: 42682 | D3: 42685 | E3: Second Class | F3: CG-12520 | G3: Claire Gute | H3: Consumer | I3: United States | J3: Henderson | K3: Kentucky | L3: 42420 | M3: South | N3: FUR-CH-10000454 | O3: Furniture | P3: Chairs | Q3: Hon Deluxe Fabric Upholstered Stacking Chairs, Rounded Back | R3: 731.94 | S3: 3 | T3: 0 | U3: 219.582
A4: 3 | B4: CA-2016-138688 | C4: 42533 | D4: 42537 | E4: Second Class | F4: DV-13045 | G4: Darrin Van Huff | H4: Corporate | I4: United States | J4: Los Angeles | K4: California | L4: 90036 | M4: West | N4: OFF-LA-10000240 | O4: Office Supplies | P4: Labels | Q4: Self-Adhesive Address Labels for Typewriters by Universal | R4: 14.62 | S4: 2 | T4: 0 | U4: 6.8714
A5: 4 | B5: US-2015-108966 | C5: 42288 | D5: 42295 | E5: Standard Class | F5: SO-20335 | G5: Sean O'Donnell | H5: Consumer | I5: United States | J5: Fort Lauderdale | K5: Florida | L5: 33311 | M5: South | N5: FUR-TA-10000577 | O5: Furniture | P5: Tables | Q5: Bretford CR4500 Series Slim Rectangular Table | R5: 957.5775 | S5: 5 | T5: 0.45 | U5: -383.031
A6: 5 | B6: US-2015-108966 | C6: 42288 | D6: 42295 | E6: Standard Class | F6: SO-20335 | G6: Sean O'Donnell | H6: Consumer | I6: United States | J6: Fort Lauderdale | K6: Florida | L6: 33311 | M6: South | N6: OFF-ST-10000760 | O6: Office Supplies | P6: Storage | Q6: Eldon Fold 'N Roll Cart System | R6: 22.368 | S6: 2 | T6: 0.2 | U6: 2.5164
A7: 6 | B7: CA-2014-115812 | C7: 41799 | D7: 41804 | E7: Standard Class | F7: BH-11710 | G7: Brosina Hoffman | H7: Consumer | I7: United States | J7: Los Angeles | K7: California | L7: 90032 | M7: West | N7: FUR-FU-10001487 | O7: Furniture | P7: Furnishings | Q7: Eldon Expressions Wood and Plastic Desk Accessories, Cherry Wood | R7: 48.86 | S7: 7 | T7: 0 | U7: 14.1694
A8: 7 | B8: CA-2014-115812 | C8: 41799 | D8: 41804 | E8: Standard Class | F8: BH-11710 | G8: Brosina Hoffman | H8: Consumer | I8: United States | J8: Los Angeles | K8: California | L8: 90032 | M8: West | N8: OFF-AR-10002833 | O8: Office Supplies | P8: Art | Q8: Newell 322 | R8: 7.28 | S8: 4 | T8: 0 | U8: 1.9656
A9: 8 | B9: CA-2014-115812 | C9: 41799 | D9: 41804 | E9: Standard Class | F9: BH-11710 | G9: Brosina Hoffman | H9: Consumer | I9: United States | J9: Los Angeles | K9: California | L9: 90032 | M9: West | N9: TEC-PH-10002275 | O9: Technology | P9: Phones | Q9: Mitel 5320 IP Phone VoIP phone | R9: 907.152 | S9: 6 | T9: 0.2 | U9: 90.7152
A10: 9 | B10: CA-2014-115812 | C10: 41799 | D10: 41804 | E10: Standard Class | F10: BH-11710 | G10: Brosina Hoffman | H10: Consumer | I10: United States | J10: Los Angeles | K10: California | L10: 90032 | M10: West | N10: OFF-BI-10003910 | O10: Office Supplies | P10: Binders | Q10: DXL Angle-View Binders with Locking Rings by Samsill | R10: 18.504 | S10: 3 | T10: 0.2 | U10: 5.7825
A11: 10 | B11: CA-2014-115812 | C11: 41799 | D11: 41804 | E11: Standard Class | F11: BH-11710 | G11: Brosina Hoffman | H11: Consumer | I11: United States | J11: Los Angeles | K11: California | L11: 90032 | M11: West | N11: OFF-AP-10002892 | O11: Office Supplies | P11: Appliances | Q11: Belkin F5C206VTEL 6 Outlet Surge | R11: 114.9 | S11: 5 | T11: 0 | U11: 34.47
A12: 11 | B12: CA-2014-115812 | C12: 41799 | D12: 41804 | E12: Standard Class | F12: BH-11710 | G12: Brosina Hoffman | H12: Consumer | I12: United States | J12: Los Angeles | K12: California | L12: 90032 | M12: West | N12: FUR-TA-10001539 | O12: Furniture | P12: Tables | Q12: Chromcraft Rectangular Conference Tables | R12: 1706.184 | S12: 9 | T12: 0.2 | U12: 85.3092
A13: 12 | B13: CA-2014-115812 | C13: 41799 | D13: 41804 | E13: Standard Class | F13: BH-11710 | G13: Brosina Hoffman | H13: Consumer | I13: United States | J13: Los Angeles | K13: California | L13: 90032 | M13: West | N13: TEC-PH-10002033 | O13: Technology | P13: Phones | Q13: Konftel 250 Conference phone - Charcoal black | R13: 911.424 | S13: 4 | T13: 0.2 | U13: 68.3568
... A9995: 9994 | B9995: CA-2017-119914 | C9995: 42859 | D9995: 42864 | E9995: Second Class | F9995: CC-12220 | G9995: Chris Cortes | H9995: Consumer | I9995: United States | J9995: Westminster | K9995: California | L9995: 92683 | M9995: West | N9995: OFF-AP-10002684 | O9995: Office Supplies | P9995: Appliances | Q9995: Acco 7-Outlet Masterpiece Power Center, Wihtout Fax/Phone Line Protection | R9995: 243.16 | S9995: 2 | T9995: 0 | U9995: 72.948

Sheet LOOKUP
A1: Customer Name | B1: Region | C1: Sales
A2: Brosina Hoffman | B2: =VLOOKUP(A2,'Raw Data'!G:R,7,FALSE) -> West | C2: =VLOOKUP(A2,'Raw Data'!G:R,12,FALSE) -> 48.86
A3: Harold Pawlan | B3: =VLOOKUP(A3,'Raw Data'!G:R,7,FALSE) -> Central | C3: =VLOOKUP(A3,'Raw Data'!G:R,12,FALSE) -> 68.81
A4: Tracy Blumstein | B4: =VLOOKUP(A4,'Raw Data'!G:R,7,FALSE) -> East | C4: =VLOOKUP(A4,'Raw Data'!G:R,12,FALSE) -> 3083.43

Sheet XLOOKUP
A1: Order ID | B1: Customer Name
A2: CA-2014-115812 | B2: =VLOOKUP(A2,'Raw Data'!B:R,6,FALSE) -> Brosina Hoffman
A3: US-2015-118983 | B3: =VLOOKUP(A3,'Raw Data'!B:R,6,FALSE) -> Harold Pawlan
A4: US-2015-150630 | B4: =VLOOKUP(A4,'Raw Data'!B:R,6,FALSE) -> Tracy Blumstein
A5: TEST-123 | B5: =VLOOKUP(A5,'Raw Data'!B:R,6,FALSE) -> #N/A

Sheet IF
A1: Sales | B1: Sales Category
A2: 250 | B2: =IF(A2>=1000,"High","Low") -> Low
A3: 750 | B3: =IF(A3>=1000,"High","Low") -> Low
A4: 1500 | B4: =IF(A4>=1000,"High","Low") -> High
A5: 3000 | B5: =IF(A5>=1000,"High","Low") -> High

Sheet SUMIFS
A1: Region | B1: Category | C1: Total Salses
A2: East | B2: Technology | C2: =SUMIFS('Raw Data'!$R:$R,'Raw Data'!$M:$M,A2,'Raw Data'!$O:$O,B3) -> 208291.2
A3: West | B3: Furniture | C3: =SUMIFS('Raw Data'!$R:$R,'Raw Data'!$M:$M,A3,'Raw Data'!$O:$O,B3) -> 252612.74
A4: South | B4: Office Supplies | C4: =SUMIFS('Raw Data'!$R:$R,'Raw Data'!$M:$M,A4,'Raw Data'!$O:$O,B3) -> 117298.68
A5: Central | B5: Technology | C5: =SUMIFS('Raw Data'!$R:$R,'Raw Data'!$M:$M,A5,'Raw Data'!$O:$O,B3) -> 163797.16

Sheet COUNTIFS
A1: Region | B1: Category | C1: Number of Records
A2: East | B2: Technology | C2: =COUNTIFS('Raw Data'!$M:$M,A2,'Raw Data'!$O:$O,B2) -> 535
A3: West | B3: Furniture | C3: =COUNTIFS('Raw Data'!$M:$M,A3,'Raw Data'!$O:$O,B2) -> 599
A4: South | B4: Office Supplies | C4: =COUNTIFS('Raw Data'!$M:$M,A4,'Raw Data'!$O:$O,B2) -> 293
A5: Central | B5: Technology | C5: =COUNTIFS('Raw Data'!$M:$M,A5,'Raw Data'!$O:$O,B2) -> 420

Sheet Text Functions
A1: Customer Name | B1: LEFT | C1: RIGHT | D1: LEN | E1: UPPER | F1: LOWER
A2: Brosian Hoffman | B2: =LEFT(A2,4) -> Bros | C2: =RIGHT(A2,4) -> man | D2: =LEN(A2) -> 16 | E2: =UPPER(A2) -> BROSIAN HOFFMAN | F2: =LOWER(A2) -> brosian hoffman

Sheet Notes
A1: Function | B1: When to Use
A2: VLOOKUP | B2: Find related information from a table
A3: XLOOKUP | B3: Look up a value and return matching information
A4: IF | B4: Make decisions based on a condition
A5: SUMIFS | B5: Add values based on one or more conditions
A6: COUNTIFS | B6: Count records based on one or more conditions
A7: LEFT | B7: Extract characters from the beginning of text
A8: RIGHT | B8: Extract characters from the end of text
A9: LEN | B9: Count the number of characters
A10: UPPER | B10: Convert text to uppercase
